Workbook

Sheet journal_to_ledger
A1: OLD | E1: NEW
A2: year | B2: type | C2: cr_ledger | D2: dr_ledger | E2: type | F2: cr_ledger | G2: dr_ledger | H2: description
A3: 2021 | B3: core讲师工资 | C3: 银行存款1002 | D3: core讲师工资5501 | E3: 支出OL讲师 | F3: 银行存款 | G3: 支出OL讲师
A4: 2023 | B4: OL-奖学金 | C4: 銀行存款1002 | D4: OL收入4301 | E4: T-收入OL | F4: 银行存款 | G4: 收入OL
A5: 2024 | B5: OL-奖学金 | C5: 应付OL奖助2302 | D5: 銀行存款1002 | E5: 应付OL奖助 | F5: 应付OL奖助 | G5: 银行存款 | M5: OL讲师工资 | N5: 银行存款1002 | O5: OL讲师/组委工资
A6: 2023 | B6: OL-讲师 | C6: 銀行存款1002 | D6: OL讲师工资5401 | E6: 支出OL讲师 | F6: 银行存款 | G6: 支出OL讲师 | M6: 书院讲师工资 | N6: 银行存款1002 | O6: 工作坊/书院讲师工资
A7: 2021 | B7: OL-讲师 | C7: 银行存款1002 | D7: OL讲师工资5401 | E7: 支出OL讲师 | F7: 银行存款 | G7: 支出OL讲师 | M7: 书院组委工资 | N7: 银行存款1002 | O7: 工作坊/书院组委工资
A8: 2024 | B8: OL-讲师工资 | C8: 銀行存款1002 | D8: OL讲师工资5401 | E8: 支出OL讲师 | F8: 银行存款 | G8: 支出OL讲师 | M8: 书院-FEE | N8: 银行存款1002 | O8: 工作坊/书院活动成本5101
A9: 2023 | B9: 研讨屋 | C9: 銀行存款1002 | D9: 业务活动成本5001 | E9: 支出内容运营 | F9: 银行存款 | G9: 支出内容运营 | M9: 书院讲师报销 | N9: 银行存款1002 | O9: 工作坊/书院活动成本5101
A10: 2024 | B10: 聚餐 | C10: 銀行存款1002 | D10: 业务活动成本5001 | E10: 社群维护 | F10: 银行存款 | G10: 社群维护 | M10: Workshop讲师工资 | N10: 银行存款1002 | O10: 工作坊/书院讲师工资
A11: 2022 | B11: 运营报销 | C11: 銀行存款1002 | D11: 业务活动成本5001 | E11: 支出内容运营 | F11: 银行存款 | G11: 支出内容运营
A12: 2022 | B12: 通讯 | C12: 銀行存款1002 | D12: 业务活动成本5001 | E12: 支出内容运营 | F12: 银行存款 | G12: 支出内容运营 | M12: Worshop组委工资 | N12: 银行存款1002 | O12: 工作坊/书院组委工资
A13: 2020 | B13: Veitgeist | C13: 银行存款1002 | D13: 业务活动成本5101 | E13: 支出内容运营 | F13: 银行存款 | G13: 支出内容运营 | M13: Workshop-FEE | N13: 银行存款1002 | O13: 工作坊/书院活动成本5101
A14: 2020 | B14: wage | C14: 银行存款1002 | D14: 业务活动成本5101 | E14: 组委工资 | F14: 银行存款 | G14: 组委工资 | M14: 研讨屋 | N14: 银行存款1002 | O14: 工作坊/书院活动成本5101
A15: 2020 | B15: Workshop-WAGE | C15: 银行存款1002 | D15: 业务活动成本5101 | E15: 支出SC组委 | F15: 银行存款 | G15: 支出SC组委 | M15: OL押金 | N15: 其他应付款 | O15: 银行存款
A16: 2020 | B16: 报销 | C16: 银行存款1002 | D16: 业务活动成本5101 | E16: 支出SC运营 | F16: 银行存款 | G16: 支出SC运营 | M16: OL押金 | N16: 银行存款 | O16: 其他应付款
A17: 2020 | B17: 讲师 | C17: 银行存款1002 | D17: 业务活动成本5101 | E17: 支出OL讲师 | F17: 银行存款 | G17: 支出OL讲师 | M17: OL退费 | N17: 银行存款1002 | O17: 提供服务收入4301
A18: 2024 | B18: 书院住宿 | C18: 銀行存款1002 | D18: 书院讲师组委工资5301 | E18: 支出SC运营 | F18: 银行存款 | G18: 支出SC运营 | M18: Workshop退费 | N18: 银行存款1002 | O18: 提供服务收入4301
A19: 2024 | B19: 书院工资 | C19: 銀行存款1002 | D19: 书院讲师组委工资5301 | E19: 支出SC讲师 | F19: 银行存款 | G19: 支出SC讲师 | M19: 书院退费 | N19: 银行存款1002 | O19: 提供服务收入4301
A20: 2024 | B20: 书院报销 | C20: 銀行存款1002 | D20: 书院运营成本5101 | E20: 支出SC运营 | F20: 银行存款 | G20: 支出SC运营 | M20: 书院优惠 | N20: 其他应付款 | O20: 银行存款
A21: 2024 | B21: 书院场地 | C21: 銀行存款1002 | D21: 书院运营成本5101 | E21: 支出SC运营 | F21: 银行存款 | G21: 支出SC运营
A22: 2024 | B22: 书院运营 | C22: 銀行存款1002 | D22: 书院运营成本5101 | E22: 支出SC运营 | F22: 银行存款 | G22: 支出SC运营 | M22: 网站 | N22: 银行存款1002 | O22: 管理费用5201
A23: 2020 | B23: OL-D | C23: 银行存款1002 | D23: 其他应付款2209 | E23: T-应付OL押金 | F23: 银行存款 | G23: 应付OL押金 | M23: 服务费 | N23: 银行存款1002 | O23: 管理费用5201
A24: 2021 | B24: OL-D | C24: 银行存款1002 | D24: 其他应付款2209 | E24: T-应付OL押金 | F24: 银行存款 | G24: 应付OL押金 | M24: Promo | N24: 银行存款1002 | O24: 管理费用5201
A25: 2022 | B25: OL-D | C25: 銀行存款1002 | D25: 其他應付款(押金)2209 | E25: 应付OL押金 | F25: 银行存款 | G25: 应付OL押金
A26: 2023 | B26: OL-D | C26: 銀行存款1002 | D26: 其他應付款(押金)2209 | E26: 应付OL押金 | F26: 银行存款 | G26: 应付OL押金 | M26: 退税 | N26: 应交税金2206 | O26: 银行存款1002
A27: 2024 | B27: OL-D | C27: 銀行存款1002 | D27: 其他應付款(押金)2209 | E27: 应付OL押金 | F27: 银行存款 | G27: 应付OL押金 | M27: 权益变动 | N27: 非限定性净资产3101 | O27: 银行存款1002
A28: 2023 | B28: OL-D&OL助学金 | C28: 銀行存款1002 | D28: 其他應付款(押金)2209 | E28: 应付OL押金 | F28: 银行存款 | G28: 应付OL押金 | M28: 转账 | N28: 银行存款1002 | O28: 银行存款1002
A29: 2024 | B29: 换汇-3000刀 | C29: 銀行存款1002 | D29: 其他貨幣資金1009 | E29: 银行存款 | F29: 银行存款 | G29: 其他货币资金
A30: 2023 | B30: 书院-助学金 | C30: 銀行存款1002 | D30: 工作坊/书院收入4201 | E30: 应付SC奖助 | F30: 银行存款 | G30: 应付SC奖助
A31: 2021 | B31: workshop-工资 | C31: 银行存款1002 | D31: 工作坊讲师工资5301 | E31: 支出SC讲师 | F31: 银行存款 | G31: 支出SC讲师
A32: 2023 | B32: 书院-组委讲师 | C32: 銀行存款1002 | D32: 工作坊讲师工资5301 | E32: 支出SC组委 | F32: 银行存款 | G32: 支出SC组委
A33: 2023 | B33: 书院-讲师组委 | C33: 銀行存款1002 | D33: 工作坊讲师工资5301 | E33: 支出SC讲师 | F33: 银行存款 | G33: 支出SC讲师
A34: 2023 | B34: 书院-运营 | C34: 銀行存款1002 | D34: 工作坊讲师工资5301 | E34: 支出SC运营 | F34: 银行存款 | G34: 支出SC运营
A35: 2023 | B35: 书院-酒店 | C35: 銀行存款1002 | D35: 工作坊讲师工资5301 | E35: 支出SC运营 | F35: 银行存款 | G35: 支出SC运营
A36: 2023 | B36: ? | C36: 銀行存款1002 | D36: 工作坊运营成本5101 | E36: 支出SC运营 | F36: 银行存款 | G36: 支出SC运营
A37: 2023 | B37: 书院-物料 | C37: 銀行存款1002 | D37: 工作坊运营成本5101 | E37: 支出SC运营 | F37: 银行存款 | G37: 支出SC运营
A38: 2020 | B38: 缴税 | C38: 银行存款1002 | D38: 所得税费用5402 | E38: 所得税税款 | F38: 银行存款 | G38: 所得税税款
A39: 2020 | B39: OL-A | C39: 银行存款1002 | D39: 提供服务收入4301 | E39: T-收入OL | F39: 银行存款 | G39: 收入OL
A40: 2024 | B40: 播客 | C40: 銀行存款1002 | D40: 播客/研讨屋5501 | E40: 支出内容运营 | F40: 银行存款 | G40: 支出内容运营
... A66: 2024 | B66: ？ | C66: 管理費用5201 | D66: 銀行存款1002 | E66: 管理费用 | F66: 银行存款 | G66: 管理费用
A67: 2023 | B67: / | D67: 銀行存款1002 | E67: /
A68: 2022 | B68: OL | C68: OL收入4301 | D68: 銀行存款1002 | E68: 收入OL | F68: 收入OL | G68: 银行存款
A69: 2023 | B69: OL | C69: OL收入4301 | D69: 銀行存款1002 | E69: 收入OL | F69: 收入OL | G69: 银行存款
A70: 2024 | B70: OL | C70: OL收入4301 | D70: 銀行存款1002 | E70: 收入OL | F70: 收入OL | G70: 银行存款
A71: 2022 | B71: OL-N | C71: OL收入4301 | D71: 銀行存款1002 | E71: 收入OL | F71: 收入OL | G71: 银行存款
A72: 2023 | B72: OL-N | C72: OL收入4301 | D72: 銀行存款1002 | E72: 收入OL | F72: 收入OL | G72: 银行存款
A73: 2024 | B73: OL押金 | C73: 其他應付款(押金)2209 | D73: 銀行存款1002 | E73: 应付OL押金 | F73: 银行存款 | G73: 应付OL押金
A74: 2022 | B74: 书院 | C74: 工作坊/书院收入4201 | D74: 銀行存款1002 | E74: 收入SC | F74: 收入SC | G74: 银行存款
A75: 2023 | B75: 书院 | C75: 工作坊/书院收入4201 | D75: 銀行存款1002 | E75: 收入SC | F75: 收入SC | G75: 银行存款
A76: 2024 | B76: 书院 | C76: 工作坊/书院收入4201 | D76: 銀行存款1002 | E76: 收入SC | F76: 收入SC | G76: 银行存款
A77: 2024 | B77: 书院学费 | C77: 工作坊/书院收入4201 | D77: 銀行存款1002 | E77: 收入SC | F77: 收入SC | G77: 银行存款
A78: 2022 | B78: 余利宝收益发放 | C78: 投資收益4601 | D78: 銀行存款1002 | E78: 投资收益 | F78: 投资收益 | G78: 银行存款
A79: 2023 | B79: 余利宝收益发放 | C79: 投資收益4601 | D79: 銀行存款1002 | E79: 投资收益 | F79: 投资收益 | G79: 银行存款
... A98: 2020 | B98: 捐赠 | C98: 捐赠收入4101 | D98: 银行存款1002 | E98: 捐赠收入 | F98: 捐赠收入 | G98: 银行存款
A99: 2020 | B99: 收费 | C99: 提供服务收入4301 | D99: 银行存款1002 | H99: 不适用
A100: 2020 | B100: 权益变动 | C100: 非限定性净资产3101 | D100: 银行存款1002 | E100: 权益变动 | F100: 权益变动 | G100: 银行存款
A101: 2021 | B101: 结息 | C101: 投资收益4601 | D101: 银行存款1002 | E101: 投资收益 | F101: 投资收益 | G101: 银行存款
A102: 2021 | B102: 聚会 | C102: 其他收入4901 | D102: 银行存款1002 | E102: 捐赠收入 | F102: 捐赠收入 | G102: 银行存款
A103: 2020 | B103: 聚会（筹款？） | C103: 提供服务收入4301 | D103: 银行存款1002 | E103: 捐赠收入 | F103: 捐赠收入 | G103: 银行存款
A104: 2021 | B104: 赞赏 | C104: 捐赠收入4101 | D104: 银行存款1002 | E104: 捐赠收入 | F104: 捐赠收入 | G104: 银行存款
A105: 2020 | B105: 赞赏码 | C105: 捐赠收入4101 | D105: 银行存款1002 | E105: 捐赠收入 | F105: 捐赠收入 | G105: 银行存款
A106: 2020 | B106: 转账 | C106: 银行存款1002 | D106: 银行存款1002 | E106: / | F106: 银行存款 | G106: 银行存款
A107: 2020 | B107: 还款 | C107: 短期借款2101 | D107: 银行存款1002 | E107: 短期借款 | F107: 银行存款 | G107: 短期借款
A108: 2020 | B108: 退税 | C108: 应交税金2206 | D108: 银行存款1002 | E108: 应付税款 | F108: 应付税款 | G108: 银行存款
A109: 2021 | B109: 酒水 | C109: 其他收入4901 | D109: 银行存款1002 | E109: 捐赠收入 | F109: 捐赠收入 | G109: 银行存款
A110: 2021 | B110: 理事出资变动 | C110: 银行存款1002 | D110: 非限定性净资产3101 | E110: T-权益变动 | F110: 银行存款 | G110: 权益变动
A111: 2020 | B111: INVEST | E111: /
A112: 2024 | B112: to支付宝 | E112: / | F112: 银行存款 | G112: 银行存款
A113: 2020 | B113: 余利宝 | E113: / | F113: 投资收益 | G113: 银行存款
A114: 2021 | B114: 余利宝 | E114: / | F114: 投资收益 | G114: 银行存款
A115: 2022 | B115: 余利宝 | E115: / | F115: 投资收益 | G115: 银行存款
A116: 2023 | B116: 余利宝 | E116: /
A117: 2024 | B117: 余利宝 | E117: / | F117: 投资收益 | G117: 银行存款
A118: 2024 | B118: 余利宝转出到支付宝 | E118: / | F118: 银行存款 | G118: 银行存款
A119: 2020 | B119: 借款还款 | E119: T-短期借款 | F119: 短期借款 | G119: 银行存款
A120: 2020 | B120: 基金申购，转入基金账户 | E120: / | F120: 银行存款 | G120: 银行存款
A121: 2021 | B121: 基金申购，转入基金账户 | E121: / | F121: 银行存款 | G121: 银行存款
A122: 2022 | B122: 基金申购，转入基金账户 | E122: / | F122: 银行存款 | G122: 银行存款
A123: 2020 | B123: 基金赎回，基金账户转出 | E123: / | F123: 银行存款 | G123: 银行存款
A124: 2021 | B124: 基金赎回，基金账户转出 | E124: / | F124: 银行存款 | G124: 银行存款
A125: 2022 | B125: 基金赎回，基金账户转出 | E125: / | F125: 银行存款 | G125: 银行存款
A126: 2024 | B126: 对公->支付宝 | E126: / | F126: 银行存款 | G126: 银行存款
A127: 2022 | B127: 支付宝余额自动转入 | E127: / | F127: 银行存款 | G127: 银行存款
A128: 2023 | B128: 支付宝余额自动转入 | E128: / | F128: 银行存款 | G128: 银行存款
... A133: 2024 | B133: 转出到支付宝余额 | E133: / | F133: 银行存款 | G133: 银行存款
A974: 2024 | B974: 捐赠收入 | C974: 捐贈收入4020 | D974: 銀行存款1002 | E974: 捐赠收入 | F974: 捐赠收入 | G974: 银行存款 | H974: 捐赠/打赏收入
A975: 2024 | B975: 社群维护 | C975: 銀行存款1002 | D975: 社群维护5030 | E975: 社群维护 | F975: 银行存款 | G975: 社群维护 | H975: 社群活动/维护费用
A976: 2024 | B976: 宣传推广 | C976: 銀行存款1002 | D976: 宣传推广5020 | E976: 宣传推广 | F976: 银行存款 | G976: 宣传推广 | H976: 宣传/推广费用
A977: 2024 | B977: 应付OL押金 | C977: 应付OL押金2301 | D977: 銀行存款1002 | E977: 应付OL押金 | F977: 应付OL押金 | G977: 银行存款 | H977: 收取线上课程押金
A978: 2024 | B978: 应付OL奖助 | C978: 应付OL奖助2302 | D978: 銀行存款1002 | E978: 应付OL奖助 | F978: 应付OL奖助 | G978: 银行存款 | H978: 发放线上课程奖助学金
A979: 2024 | B979: 支出OL讲师 | C979: 銀行存款1002 | D979: 支出OL讲师5301 | E979: 支出OL讲师 | F979: 银行存款 | G979: 支出OL讲师 | H979: 支付线上课程讲师工资
A980: 2024 | B980: T-收入OL | C980: 銀行存款1002 | D980: OL收入4301 | E980: T-收入OL | F980: 银行存款 | G980: 收入OL | H980: 线上课程退款（收入冲回）
A981: 2024 | B981: 律师费 | C981: 銀行存款1002 | D981: 管理費用5000 | E981: 律师费 | F981: 银行存款 | G981: 管理费用 | H981: 律师费/法律服务费
A982: 2020 | B982: 余利宝收益发放 | C982: 投資收益4030 | D982: 銀行存款1002 | E982: 投资收益 | F982: 投资收益 | G982: 银行存款 | H982: 余利宝每日收益
A983: 2021 | B983: 余利宝收益发放 | C983: 投資收益4030 | D983: 銀行存款1002 | E983: 投资收益 | F983: 投资收益 | G983: 银行存款 | H983: 余利宝每日收益
A984: 2020 | B984: 基金收益 | C984: 投資收益4030 | D984: 銀行存款1002 | E984: 投资收益 | F984: 投资收益 | G984: 银行存款 | H984: 货币基金每日收益
A985: 2024 | B985: 收入OL | C985: OL收入4301 | D985: 銀行存款1002 | E985: 收入OL | F985: 收入OL | G985: 银行存款 | H985: Q4线上课程学费收入
... A1016: 2021 | B1016: workshop | C1016: 收入SC4200 | D1016: 銀行存款1002 | E1016: 收入SC | F1016: 收入SC | G1016: 银行存款 | H1016: Workshop工作坊收入
A1017: 2020 | B1017: Workshop-FEE | E1017: 收入SC | F1017: 收入SC | G1017: 银行存款 | H1017: Workshop fee income
...

Sheet ledger_new
A1: ledger name | B1: ledger ID | C1: #1 | E1: #2 | G1: #3 | I1: #4 | K1: 备注
A2: 银行存款 | B2: 1100 | C2: 1 | D2: 资产 | E2: 1 | F2: 人民币银行账户存款
A3: 其他货币资金 | B3: 1200 | E3: 2 | F3: 其他货币资金
A4: 短期借款 | B4: 2010 | C4: 2 | D4: 应付款 | E4: 0 | F4: 组织运营 | G4: 1 | H4: 短期借款
A5: 应付SC押金 | B5: 2201 | E5: 2 | F5: 线下活动 | G5: 0 | H5: 书院/工作坊 | I5: 1 | J5: 押金
A6: 应付SC奖助 | B6: 2202 | I6: 2 | J6: 助学金/奖学金
A7: 应付税款 | B7: 2209 | I7: 9 | J7: 应付税款 | K7: （退税）
A8: 应付OL押金 | B8: 2301 | E8: 3 | F8: 线上活动 | G8: 0 | H8: 线上课程 | I8: 1 | J8: 押金
A9: 应付OL奖助 | B9: 2302 | I9: 2 | J9: 助学金/奖学金
A10: 权益变动 | B10: 3000 | C10: 3 | D10: 权益 | E10: 0 | G10: 0
A11: 捐赠收入 | B11: 4020 | C11: 4 | D11: 收入 | E11: 0 | F11: 组织运营 | G11: 2 | H11: 捐赠收入
A12: 投资收益 | B12: 4030 | G12: 3 | H12: 投资收益
A13: 收入SC | B13: 4200 | E13: 2 | F13: 线下活动 | G13: 0 | H13: 书院/工作坊
A14: 收入OL | B14: 4300 | E14: 3 | F14: 线上活动 | G14: 0 | H14: 线上课程
A15: 管理费用 | B15: 5000 | C15: 5 | D15: 支出 | E15: 0 | F15: 组织运营 | G15: 0 | H15: 管理费用
A16: 组委工资 | B16: 5010 | G16: 1 | H16: 组委工资
A17: 宣传推广 | B17: 5020 | G17: 2 | H17: 宣传推广
A18: 社群维护 | B18: 5030 | G18: 3 | H18: 社群维护
A19: 所得税税款 | B19: 5090 | G19: 9 | H19: 所得税税款
A20: 支出SC讲师 | B20: 5201 | E20: 2 | F20: 线下活动 | G20: 0 | H20: 书院/工作坊 | I20: 1 | J20: 讲师
A21: 支出SC组委 | B21: 5202 | I21: 2 | J21: 组委
A22: 支出SC运营 | B22: 5203 | I22: 3 | J22: 运营
A23: 支出OL讲师 | B23: 5301 | E23: 3 | F23: 线上活动 | G23: 0 | H23: 线上课程 | I23: 1 | J23: 讲师
A24: 支出OL组委 | B24: 5302 | I24: 2 | J24: 组委
A25: 支出OL运营 | B25: 5303 | I25: 3 | J25: 运营
A26: 支出内容运营 | B26: 5310 | G26: 1 | H26: 播客/研讨屋/通讯

Sheet ledger_old
A1: OLD
A2: year | B2: ledger name | C2: ledger ID
A3: 2021 | B3: core讲师工资 | C3: 5501
A4: 2022 | B4: core讲师工资 | C4: 5501
A5: 2023 | B5: core讲师工资 | C5: 5501
A6: 2021 | B6: OL收入 | C6: 4301
A7: 2022 | B7: OL收入 | C7: 4301
A8: 2023 | B8: OL收入 | C8: 4301
A9: 2024 | B9: OL收入 | C9: 4301
A10: 2021 | B10: OL讲师工资 | C10: 5401
A11: 2022 | B11: OL讲师工资 | C11: 5401
A12: 2023 | B12: OL讲师工资 | C12: 5401
A13: 2024 | B13: OL讲师工资 | C13: 5401
A14: 2020 | B14: 业务活动成本 | C14: 5101
... A104: 2021 | B104: 预收账款 | C104: 2203

Sheet journal
A1: OLD | D1: NEW
A2: year | B2: 摘要 | C2: type | D2: type
A3: 2022 | B3: 余利宝-基金赎回，转账到支付宝 | C3: 余利宝 | D3: =VLOOKUP(C3,journal_to_ledger!B:E,4,FALSE)
A4: 2022 | B4: 课程押金，感谢参与～ | C4: OL-D | D4: =VLOOKUP(C4,journal_to_ledger!B:E,4,FALSE)
A5: 2022 | B5: 余利宝自动转入 | C5: 余利宝 | D5: =VLOOKUP(C5,journal_to_ledger!B:E,4,FALSE)
A6: 2022 | B6: 唯理教育简报年终幸运读者，感谢支持～ | C6: 通讯 | D6: =VLOOKUP(C6,journal_to_ledger!B:E,4,FALSE)
A7: 2022 | B7: OL30 TA | C7: 工资 | D7: =VLOOKUP(C7,journal_to_ledger!B:E,4,FALSE)
A8: 2022 | B8: OL30 运营 | C8: 工资 | D8: =VLOOKUP(C8,journal_to_ledger!B:E,4,FALSE)
A9: 2022 | B9: 12月月度简报 | C9: 工资 | D9: =VLOOKUP(C9,journal_to_ledger!B:E,4,FALSE)
A10: 2022 | B10: 公众号活动报销 | C10: 报销 | D10: =VLOOKUP(C10,journal_to_ledger!B:E,4,FALSE)
A11: 2022 | B11: 服务器报销 | C11: / | D11: =VLOOKUP(C11,journal_to_ledger!B:E,4,FALSE)
A12: 2022 | B12: 报销服务器 | C12: 报销 | D12: =VLOOKUP(C12,journal_to_ledger!B:E,4,FALSE)
A13: 2022 | B13: 线上课程TA | C13: 工资 | D13: =VLOOKUP(C13,journal_to_ledger!B:E,4,FALSE)
A14: 2022 | B14: 回顾微信推送 | C14: 工资 | D14: =VLOOKUP(C14,journal_to_ledger!B:E,4,FALSE)
... A20: 2022 | B20: OL29录像 | C20: OL-N | D20: =VLOOKUP(C20,journal_to_ledger!B:E,4,FALSE)
A21: 2022 | C21: 基金收益 | D21: =VLOOKUP(C21,journal_to_ledger!B:E,4,FALSE)
A22: 2022 | C22: 基金赎回，基金账户转出 | D22: =VLOOKUP(C22,journal_to_ledger!B:E,4,FALSE)
A23: 2022 | C23: 基金申购，转入基金账户 | D23: =VLOOKUP(C23,journal_to_ledger!B:E,4,FALSE)
A24: 2022 | B24: / | C24: 赞赏 | D24: =VLOOKUP(C24,journal_to_ledger!B:E,4,FALSE)
A25: 2022 | B25: 商务卡-单位结算卡年费 | C25: 运营 | D25: =VLOOKUP(C25,journal_to_ledger!B:E,4,FALSE)
A26: 2022 | B26: 结息 | C26: 结息 | D26: =VLOOKUP(C26,journal_to_ledger!B:E,4,FALSE)
A27: 2022 | B27: OL32 李玉青 | C27: OL | D27: =VLOOKUP(C27,journal_to_ledger!B:E,4,FALSE)
A28: 2022 | B28: OL32刘熙宁 | C28: OL | D28: =VLOOKUP(C28,journal_to_ledger!B:E,4,FALSE)
A29: 2022 | B29: OL32+陈轩 | C29: OL | D29: =VLOOKUP(C29,journal_to_ledger!B:E,4,FALSE)
A30: 2022 | B30: 转账 | C30: OL | D30: =VLOOKUP(C30,journal_to_ledger!B:E,4,FALSE)
A31: 2022 | B31: OL32 谈鹤 | C31: OL | D31: =VLOOKUP(C31,journal_to_ledger!B:E,4,FALSE)
A32: 2022 | B32: OL32朱文正 | C32: OL | D32: =VLOOKUP(C32,journal_to_ledger!B:E,4,FALSE)
A33: 2022 | B33: OL32 向翌晨 | C33: OL | D33: =VLOOKUP(C33,journal_to_ledger!B:E,4,FALSE)
A34: 2022 | B34: OL32+范荣庆 押金 | C34: OL | D34: =VLOOKUP(C34,journal_to_ledger!B:E,4,FALSE)
A35: 2022 | B35: OL32+范荣庆 学费 | C35: OL | D35: =VLOOKUP(C35,journal_to_ledger!B:E,4,FALSE)
... A167: 2022 | B167: 企业网银高级版 | C167: 运营 | D167: =VLOOKUP(C167,journal_to_ledger!B:E,4,FALSE)
A168: 2022 | C168: 结息 | D168: =VLOOKUP(C168,journal_to_ledger!B:E,4,FALSE)
A169: 2022 | B169: 武外英中张笑晗唯理线上书院缴费 | C169: 书院 | D169: =VLOOKUP(C169,journal_to_ledger!B:E,4,FALSE)
A170: 2022 | B170: 陈依唯，广东碧桂园学校 | C170: 书院 | D170: =VLOOKUP(C170,journal_to_ledger!B:E,4,FALSE)
A171: 2022 | B171: 南京大学徐静 | C171: 书院 | D171: =VLOOKUP(C171,journal_to_ledger!B:E,4,FALSE)
A172: 2022 | B172: 董泠君广州华附国际部HFI | C172: 书院 | D172: =VLOOKUP(C172,journal_to_ledger!B:E,4,FALSE)
A173: 2022 | B173: 赵姗姗深圳国际交流学院 | C173: 书院 | D173: =VLOOKUP(C173,journal_to_ledger!B:E,4,FALSE)
A174: 2022 | B174: 王柯颖，济南外国语学校 | C174: 书院 | D174: =VLOOKUP(C174,journal_to_ledger!B:E,4,FALSE)
A175: 2022 | B175: 备注是赵一伟SantaMonicaCollege | C175: 书院 | D175: =VLOOKUP(C175,journal_to_ledger!B:E,4,FALSE)
A176: 2022 | B176: 侯靖淇北师大实验中学 | C176: 书院 | D176: =VLOOKUP(C176,journal_to_ledger!B:E,4,FALSE)
A177: 2022 | B177: EasonYang/TrinityCollegeSch | C177: 书院 | D177: =VLOOKUP(C177,journal_to_ledger!B:E,4,FALSE)
A178: 2022 | B178: 张画 | C178: 书院 | D178: =VLOOKUP(C178,journal_to_ledger!B:E,4,FALSE)
A179: 2022 | B179: ol35退押金 | C179: OL-D | D179: =VLOOKUP(C179,journal_to_ledger!B:E,4,FALSE)
A180: 2022 | B180: ol32退押金 | C180: OL-D | D180: =VLOOKUP(C180,journal_to_ledger!B:E,4,FALSE)
... A271: 2022 | B271: ol35押金，感谢参与～ | C271: OL-D | D271: =VLOOKUP(C271,journal_to_ledger!B:E,4,FALSE)
A272: 2022 | C272: OL | D272: =VLOOKUP(C272,journal_to_ledger!B:E,4,FALSE)
A273: 2022 | B273: ol35讲师工资 | C273: OL | D273: =VLOOKUP(C273,journal_to_ledger!B:E,4,FALSE)
A274: 2022 | B274: OL42-陆然诚 | C274: OL | D274: =VLOOKUP(C274,journal_to_ledger!B:E,4,FALSE)
A275: 2022 | B275: Ol42 高肖峰 | C275: OL | D275: =VLOOKUP(C275,journal_to_ledger!B:E,4,FALSE)
A276: 2022 | B276: OL42+陈轩 | C276: OL | D276: =VLOOKUP(C276,journal_to_ledger!B:E,4,FALSE)
A277: 2022 | B277: 陈义佳 1192380690@qq.com 线上课程学费及押金 | C277: OL | D277: =VLOOKUP(C277,journal_to_ledger!B:E,4,FALSE)
A278: 2022 | B278: OL42郑凯文 | C278: OL | D278: =VLOOKUP(C278,journal_to_ledger!B:E,4,FALSE)
A279: 2022 | B279: OL42+程佳慧 | C279: OL | D279: =VLOOKUP(C279,journal_to_ledger!B:E,4,FALSE)
A280: 2022 | B280: 罐头 OL42：法西斯主义研究 | C280: OL | D280: =VLOOKUP(C280,journal_to_ledger!B:E,4,FALSE)
A281: 2022 | B281: OL42 张凯琳课程费+押金 | C281: OL | D281: =VLOOKUP(C281,journal_to_ledger!B:E,4,FALSE)
A282: 2022 | B282: OL42 陈祯民 | C282: OL | D282: =VLOOKUP(C282,journal_to_ledger!B:E,4,FALSE)
A283: 2022 | B283: 书院coteach工资 谢谢参与～ | C283: 书院 | D283: =VLOOKUP(C283,journal_to_ledger!B:E,4,FALSE)
A284: 2022 | B284: 书院coteach工资 感谢参与～ | C284: 书院 | D284: =VLOOKUP(C284,journal_to_ledger!B:E,4,FALSE)
A285: 2022 | B285: 书院coteach工资 | C285: 书院 | D285: =VLOOKUP(C285,journal_to_ledger!B:E,4,FALSE)
A286: 2022 | C286: 书院 | D286: =VLOOKUP(C286,journal_to_ledger!B:E,4,FALSE)
A287: 2022 | B287: 服务费[20220822200040011100020006326332] | C287: 支付宝服务费 | D287: =VLOOKUP(C287,journal_to_ledger!B:E,4,FALSE)
A288: 2022 | B288: 书院参与证明报销 | C288: 书院 | D288: =VLOOKUP(C288,journal_to_ledger!B:E,4,FALSE)
A289: 2022 | B289: 多项订阅费用报销 | C289: 报销 | D289: =VLOOKUP(C289,journal_to_ledger!B:E,4,FALSE)
A290: 2022 | B290: 您好，这是我的课程费用与押金。 | C290: OL | D290: =VLOOKUP(C290,journal_to_ledger!B:E,4,FALSE)
A291: 2022 | B291: 转账 | C291: OL-N | D291: =VLOOKUP(C291,journal_to_ledger!B:E,4,FALSE)
A292: 2022 | B292: 退还押金，希望下次见到你～ | C292: OL-D | D292: =VLOOKUP(C292,journal_to_ledger!B:E,4,FALSE)
A293: 2022 | B293: 线上课程退款，希望下次见到你～ | C293: OL | D293: =VLOOKUP(C293,journal_to_ledger!B:E,4,FALSE)
A294: 2022 | B294: ol36押金，感谢参与～ | C294: OL-D | D294: =VLOOKUP(C294,journal_to_ledger!B:E,4,FALSE)
A295: 2022 | B295: 新闻实验室订阅 | C295: 运营 | D295: =VLOOKUP(C295,journal_to_ledger!B:E,4,FALSE)
A296: 2022 | B296: 讲师工资，感谢～ | C296: OL | D296: =VLOOKUP(C296,journal_to_ledger!B:E,4,FALSE)
A297: 2022 | B297: 7月 | C297: 工资 | D297: =VLOOKUP(C297,journal_to_ledger!B:E,4,FALSE)
A298: 2022 | B298: 7月工资 | C298: 工资 | D298: =VLOOKUP(C298,journal_to_ledger!B:E,4,FALSE)
... A319: 2022 | B319: OL43 Chloe Wang 王伊憬 | C319: OL | D319: =VLOOKUP(C319,journal_to_ledger!B:E,4,FALSE)
A320: 2022 | C320: 支付宝余额自动转入 | D320: =VLOOKUP(C320,journal_to_ledger!B:E,4,FALSE)
A321: 2022 | C321: 余利宝收益发放 | D321: =VLOOKUP(C321,journal_to_ledger!B:E,4,FALSE)
A322: 2022 | C322: 转出到支付宝余额 | D322: =VLOOKUP(C322,journal_to_ledger!B:E,4,FALSE)
A323: 2022 | B323: 广东碧桂园学校梁心语 | C323: 书院 | D323: =VLOOKUP(C323,journal_to_ledger!B:E,4,FALSE)
A324: 2022 | B324: 电子汇入 | C324: 书院 | D324: =VLOOKUP(C324,journal_to_ledger!B:E,4,FALSE)
A325: 2022 | B325: 李锦荣波士顿学院BostonColl | C325: 书院 | D325: =VLOOKUP(C325,journal_to_ledger!B:E,4,FALSE)
A326: 2022 | B326: 李雨桐人大附中ICC | C326: 书院 | D326: =VLOOKUP(C326,journal_to_ledger!B:E,4,FALSE)
A327: 2022 | B327: 服务费 | C327: 书院 | D327: =VLOOKUP(C327,journal_to_ledger!B:E,4,FALSE)
A328: 2022 | B328: 王安若/深国交 | C328: 书院 | D328: =VLOOKUP(C328,journal_to_ledger!B:E,4,FALSE)
A329: 2022 | B329: 大夏令营 | C329: 书院 | D329: =VLOOKUP(C329,journal_to_ledger!B:E,4,FALSE)
A330: 2022 | B330: 张奕帆青岛第五十八中学线上课报名费 | C330: 书院 | D330: =VLOOKUP(C330,journal_to_ledger!B:E,4,FALSE)
A331: 2022 | B331: 郭靖琳深圳大学 | C331: 书院 | D331: =VLOOKUP(C331,journal_to_ledger!B:E,4,FALSE)
A332: 2022 | B332: 美国波士顿东北大学吴子含 | C332: 书院 | D332: =VLOOKUP(C332,journal_to_ledger!B:E,4,FALSE)
A333: 2022 | B333: 许成阳南京外国语学校国际部2022唯理线上书院缴费 | C333: 书院 | D333: =VLOOKUP(C333,journal_to_ledger!B:E,4,FALSE)
A334: 2022 | B334: 深圳国际交流学院杨若晨 | C334: 书院 | D334: =VLOOKUP(C334,journal_to_ledger!B:E,4,FALSE)
... A574: 2023 | B574: 书院助学金 | C574: 书院-助学金 | D574: =VLOOKUP(C574,journal_to_ledger!B:E,4,FALSE)
A575: 2023 | C575: 书院-物料 | D575: =VLOOKUP(C575,journal_to_ledger!B:E,4,FALSE)
A576: 2023 | B576: 摄影7.29 | C576: 书院-物料 | D576: =VLOOKUP(C576,journal_to_ledger!B:E,4,FALSE)
A577: 2023 | B577: 摄影 | C577: 书院-物料 | D577: =VLOOKUP(C577,journal_to_ledger!B:E,4,FALSE)
A578: 2023 | B578: 摄影尾款 | C578: 书院-物料 | D578: =VLOOKUP(C578,journal_to_ledger!B:E,4,FALSE)
A579: 2023 | B579: 余款 | C579: 书院-物料 | D579: =VLOOKUP(C579,journal_to_ledger!B:E,4,FALSE)
A580: 2023 | B580: 报销打车 | C580: 书院-物料 | D580: =VLOOKUP(C580,journal_to_ledger!B:E,4,FALSE)
A581: 2023 | B581: 邮寄帆布包 | C581: 书院-物料 | D581: =VLOOKUP(C581,journal_to_ledger!B:E,4,FALSE)
A582: 2023 | B582: t恤样品 | C582: 书院-物料 | D582: =VLOOKUP(C582,journal_to_ledger!B:E,4,FALSE)
A583: 2023 | B583: 贴纸本子样品 | C583: 书院-物料 | D583: =VLOOKUP(C583,journal_to_ledger!B:E,4,FALSE)
A584: 2023 | B584: 帆布袋样品 | C584: 书院-物料 | D584: =VLOOKUP(C584,journal_to_ledger!B:E,4,FALSE)
A585: 2023 | B585: 物料购买费用 | C585: 书院-物料 | D585: =VLOOKUP(C585,journal_to_ledger!B:E,4,FALSE)
...
